wyn360_cli/__init__.py
wyn360_cli/agent.py
wyn360_cli/browser_auth.py
wyn360_cli/browser_controller.py
wyn360_cli/browser_task_executor.py
wyn360_cli/browser_use.py
wyn360_cli/cli.py
wyn360_cli/config.py
wyn360_cli/credential_manager.py
wyn360_cli/document_readers.py
wyn360_cli/session_manager.py
wyn360_cli/utils.py
wyn360_cli/vision_engine.py
wyn360_cli-0.3.59.dist-info/METADATA
wyn360_cli-0.3.59.dist-info/WHEEL
wyn360_cli-0.3.59.dist-info/entry_points.txt
wyn360_cli-0.3.59.dist-info/RECORD
