Metadata-Version: 2.4
Name: wyn360-cli
Version: 0.3.59
Summary: WYN360 - An intelligent AI coding assistant CLI tool powered by Anthropic Claude
Author: Yiqiao Yin
Author-email: yiqiao.yin@wyn-associates.com
Requires-Python: >=3.10,<4.0
Classifier: Programming Language :: Python :: 3
Classifier: Programming Language :: Python :: 3.10
Classifier: Programming Language :: Python :: 3.11
Classifier: Programming Language :: Python :: 3.12
Classifier: Programming Language :: Python :: 3.13
Classifier: Programming Language :: Python :: 3.14
Requires-Dist: Pillow (>=10.0.0)
Requires-Dist: anthropic[bedrock] (>=0.39.0)
Requires-Dist: click (>=8.1.0)
Requires-Dist: crawl4ai (>=0.7.6)
Requires-Dist: cryptography (>=42.0.0)
Requires-Dist: huggingface-hub (>=0.20.0)
Requires-Dist: numpy (>=1.24.0)
Requires-Dist: pdf2image (>=1.16.0)
Requires-Dist: playwright (>=1.40.0)
Requires-Dist: prompt-toolkit (>=3.0.0)
Requires-Dist: pydantic-ai (>=1.13.0)
Requires-Dist: pytesseract (>=0.3.10)
Requires-Dist: python-dotenv (>=1.2.1,<2.0.0)
Requires-Dist: pyyaml (>=6.0.0)
Requires-Dist: rich (>=13.0.0)
Requires-Dist: sentence-transformers (>=2.2.0)
Requires-Dist: torch (>=2.0.0)
